proc_wrapper/__init__.py
proc_wrapper/__main__.py
proc_wrapper/common_constants.py
proc_wrapper/common_utils.py
proc_wrapper/config_resolver.py
proc_wrapper/proc_wrapper.py
proc_wrapper/proc_wrapper_params.py
proc_wrapper/py.typed
proc_wrapper/runtime_metadata.py
proc_wrapper/status_updater.py
cloudreactor_procwrapper-6.0.2.dist-info/LICENSE
cloudreactor_procwrapper-6.0.2.dist-info/METADATA
cloudreactor_procwrapper-6.0.2.dist-info/WHEEL
cloudreactor_procwrapper-6.0.2.dist-info/entry_points.txt
cloudreactor_procwrapper-6.0.2.dist-info/RECORD
