Metadata-Version: 2.1
Name: cloudreactor-procwrapper
Version: 6.0.2
Summary: Wraps the execution of processes so that a service API endpoint (CloudReactor) can monitor and manage them. Also implements retries, timeouts, and secret injection from AWS into the environment.
Home-page: https://cloudreactor.io
License: Dual license, MPL 2.0 or commercial
Author: Jeff Tsay
Author-email: jeff@cloudreactor.io
Requires-Python: >=3.9,<4.0
Classifier: Development Status :: 4 - Beta
Classifier: Intended Audience :: Developers
Classifier: License :: Other/Proprietary License
Classifier: Natural Language :: English
Classifier: Operating System :: OS Independent
Classifier: Programming Language :: Python :: 3
Classifier: Programming Language :: Python :: 3.9
Classifier: Programming Language :: Python :: 3.10
Classifier: Programming Language :: Python :: 3.11
Classifier: Programming Language :: Python :: 3.12
Classifier: Programming Language :: Python :: 3.13
Classifier: Topic :: Software Development :: Libraries
Provides-Extra: allextras
Provides-Extra: aws
Provides-Extra: dotenv
Provides-Extra: ec2
Provides-Extra: jsonpath
Provides-Extra: mergedeep
Provides-Extra: yaml
Requires-Dist: boto3 (>=1.16.0) ; extra == "aws" or extra == "allextras"
Requires-Dist: ec2-metadata (>=2.14.0) ; extra == "ec2" or extra == "allextras"
Requires-Dist: jsonpath-ng (>=1.5.0) ; extra == "jsonpath" or extra == "allextras"
Requires-Dist: mergedeep (>=1.3.0) ; extra == "mergedeep" or extra == "allextras"
Requires-Dist: python-dotenv (>=0.17.0) ; extra == "dotenv" or extra == "allextras"
Requires-Dist: pyyaml (>=5.5.0) ; extra == "yaml" or extra == "allextras"
Project-URL: Bug Tracker, https://github.com/CloudReactor/cloudreactor-procwrapper/issues
Project-URL: Changelog, https://cloudreactor-procwrapper.readthedocs.io/en/latest/changelog.html
Project-URL: Documentation, https://cloudreactor-procwrapper.readthedocs.io
Project-URL: Repository, https://github.com/CloudReactor/cloudreactor-procwrapper
